text_analyzer69/__init__.py
text_analyzer69/text_analyzer69.cpython-310-x86_64-linux-gnu.so
text_analyzer69-0.1.0.dist-info/METADATA
text_analyzer69-0.1.0.dist-info/WHEEL
text_analyzer69-0.1.0.dist-info/RECORD
