Metadata-Version: 2.4
Name: text_analyzer69
Version: 0.1.0
Summary: A simple cross-platform text analyzer CLI (Rust core)
Author-email: Antigravity <ai@deepmind.com>
Requires-Python: >=3.7
